pydrawing/__init__.py
pydrawing/pydrawing.py
pydrawing/modules/__init__.py
pydrawing/modules/beautifiers/__init__.py
pydrawing/modules/beautifiers/base/__init__.py
pydrawing/modules/beautifiers/base/base.py
pydrawing/modules/beautifiers/beziercurve/__init__.py
pydrawing/modules/beautifiers/beziercurve/beziercurve.py
pydrawing/modules/beautifiers/beziercurve/potrace.exe
pydrawing/modules/beautifiers/cartoongan/__init__.py
pydrawing/modules/beautifiers/cartoongan/cartoongan.py
pydrawing/modules/beautifiers/cartoonise/__init__.py
pydrawing/modules/beautifiers/cartoonise/cartoonise.py
pydrawing/modules/beautifiers/cartoonizeface/__init__.py
pydrawing/modules/beautifiers/cartoonizeface/cartoonizeface.py
pydrawing/modules/beautifiers/cartoonizeface/facedetector/__init__.py
pydrawing/modules/beautifiers/cartoonizeface/facedetector/facedetector.py
pydrawing/modules/beautifiers/cartoonizeface/facesegmentor/__init__.py
pydrawing/modules/beautifiers/cartoonizeface/facesegmentor/facesegmentor.py
pydrawing/modules/beautifiers/characterize/__init__.py
pydrawing/modules/beautifiers/characterize/characterize.py
pydrawing/modules/beautifiers/douyineffect/__init__.py
pydrawing/modules/beautifiers/douyineffect/douyineffect.py
pydrawing/modules/beautifiers/fastneuralstyletransfer/__init__.py
pydrawing/modules/beautifiers/fastneuralstyletransfer/fastneuralstyletransfer.py
pydrawing/modules/beautifiers/geneticfitting/__init__.py
pydrawing/modules/beautifiers/geneticfitting/geneticfittingcircle.py
pydrawing/modules/beautifiers/geneticfitting/geneticfittingpolygon.py
pydrawing/modules/beautifiers/glitch/__init__.py
pydrawing/modules/beautifiers/glitch/glitch.py
pydrawing/modules/beautifiers/nostalgicstyle/__init__.py
pydrawing/modules/beautifiers/nostalgicstyle/nostalgicstyle.py
pydrawing/modules/beautifiers/noteprocessor/__init__.py
pydrawing/modules/beautifiers/noteprocessor/noteprocessor.py
pydrawing/modules/beautifiers/oilpainting/__init__.py
pydrawing-0.1.9.dist-info/LICENSE
pydrawing-0.1.9.dist-info/METADATA
pydrawing-0.1.9.dist-info/WHEEL
pydrawing-0.1.9.dist-info/top_level.txt
pydrawing-0.1.9.dist-info/zip-safe
pydrawing-0.1.9.dist-info/RECORD
