Metadata-Version: 2.1
Name: pydrawing
Version: 0.1.9
Summary: Pydrawing: Beautify your image or video.
Home-page: https://github.com/CharlesPikachu/pydrawing
Author: Zhenchao Jin
Author-email: charlesblwx@gmail.com
License: Apache License 2.0
Platform: UNKNOWN
Classifier: License :: OSI Approved :: Apache Software License
Classifier: Programming Language :: Python :: 3
Classifier: Intended Audience :: Developers
Classifier: Operating System :: OS Independent
License-File: LICENSE
Requires-Dist: opencv-python
Requires-Dist: numpy
Requires-Dist: tqdm
Requires-Dist: pillow
Requires-Dist: beautifulsoup4
Requires-Dist: imutils
